{
  "symbol": "FDN",
  "holdings": [
    {
      "symbol": "AMZN",
      "weight": 0.1024096
    },
    {
      "symbol": "META",
      "weight": 0.0913553
    },
    {
      "symbol": "NFLX",
      "weight": 0.0897793
    },
    {
      "symbol": "CSCO",
      "weight": 0.0677959
    },
    {
      "symbol": "GOOGL",
      "weight": 0.0540366
    },
    {
      "symbol": "BKNG",
      "weight": 0.0458352
    },
    {
      "symbol": "CRM",
      "weight": 0.0452453
    },
    {
      "symbol": "GOOG",
      "weight": 0.043301202
    },
    {
      "symbol": "ANET",
      "weight": 0.0417941
    },
    {
      "symbol": "NET",
      "weight": 0.0345201
    }
  ]
}