{
  "symbol": "XHE",
  "holdings": [
    {
      "symbol": "TFX",
      "weight": 0.0186242
    },
    {
      "symbol": "STAA",
      "weight": 0.018426599
    },
    {
      "symbol": "BFLY",
      "weight": 0.0184038
    },
    {
      "symbol": "MDLN",
      "weight": 0.0182678
    },
    {
      "symbol": "GKOS",
      "weight": 0.0182149
    },
    {
      "symbol": "ITGR",
      "weight": 0.0179163
    },
    {
      "symbol": "AXGN",
      "weight": 0.0178541
    },
    {
      "symbol": "LIVN",
      "weight": 0.017764699
    },
    {
      "symbol": "MASI",
      "weight": 0.0176369
    },
    {
      "symbol": "LMAT",
      "weight": 0.0175349
    }
  ]
}